__init__.py
airflow_api_client.py
airflow_connections_manager.py
sample.py
airflow_connections_manager-0.0.6.dist-info/LICENSE
airflow_connections_manager-0.0.6.dist-info/METADATA
airflow_connections_manager-0.0.6.dist-info/WHEEL
airflow_connections_manager-0.0.6.dist-info/top_level.txt
airflow_connections_manager-0.0.6.dist-info/RECORD
