Metadata-Version: 2.1
Name: airflow-connections-manager
Version: 0.0.6
Summary: Library for managing Airflow connections (aka Secrets)
Author-email: Cristiano Sarmento <cristiano.sar@gmail.com>
License: 
Project-URL: Homepage, https://github.com/cbevilaqua/airflow_connections_manager
Project-URL: Bug Tracker, https://github.com/cbevilaqua/airflow_connections_manager/issues
Classifier: Programming Language :: Python :: 3
Classifier: License :: OSI Approved :: Apache Software License
Classifier: Operating System :: OS Independent
Requires-Python: >=3.6
License-File: LICENSE
Requires-Dist: requests
